MANIFEST.in
README
__pkginfo__.py
setup.py
./setup.py
rqlquery/__init__.py
rqlquery/filter.py
rqlquery/query.py
rqlquery.egg-info/PKG-INFO
rqlquery.egg-info/SOURCES.txt
rqlquery.egg-info/dependency_links.txt
rqlquery.egg-info/requires.txt
rqlquery.egg-info/top_level.txt