Metadata-Version: 1.0
Name: rqlquery
Version: 0.1.1
Summary: Experimental ORM Query object
Home-page: http://www.cubicweb.org/project/rqlquery
Author: UNLISH S.A.S (Montpellier, FRANCE)
Author-email: christophe@unlish.com
License: LGPL
Platform: UNKNOWN
